[{"time_slot":"20:00:00","forecast_wait":11,"actual_wait":11.0},{"time_slot":"20:05:00","forecast_wait":11,"actual_wait":11.0},{"time_slot":"20:15:00","forecast_wait":11,"actual_wait":11.0},{"time_slot":"20:25:00","forecast_wait":11,"actual_wait":11.0},{"time_slot":"20:40:00","forecast_wait":11,"actual_wait":8.7},{"time_slot":"20:45:00","forecast_wait":11,"actual_wait":8.7},{"time_slot":"20:55:00","forecast_wait":11,"actual_wait":8.7},{"time_slot":"21:05:00","forecast_wait":11,"actual_wait":8.6},{"time_slot":"21:15:00","forecast_wait":11,"actual_wait":8.6},{"time_slot":"21:25:00","forecast_wait":11,"actual_wait":8.6},{"time_slot":"21:30:00","forecast_wait":11,"actual_wait":8.6},{"time_slot":"21:40:00","forecast_wait":11,"actual_wait":8.6},{"time_slot":"21:50:00","forecast_wait":11,"actual_wait":8.6},{"time_slot":"22:00:00","forecast_wait":11,"actual_wait":8.5}]