[{"time_slot":"11:05:00","forecast_wait":8,"actual_wait":5.7},{"time_slot":"11:10:00","forecast_wait":8,"actual_wait":5.7},{"time_slot":"11:20:00","forecast_wait":8,"actual_wait":5.7},{"time_slot":"11:25:00","forecast_wait":8,"actual_wait":5.7},{"time_slot":"11:30:00","forecast_wait":8,"actual_wait":5.7},{"time_slot":"11:35:00","forecast_wait":8,"actual_wait":5.7},{"time_slot":"11:40:00","forecast_wait":8,"actual_wait":5.7},{"time_slot":"11:50:00","forecast_wait":8,"actual_wait":5.7},{"time_slot":"11:55:00","forecast_wait":9,"actual_wait":5.7},{"time_slot":"12:00:00","forecast_wait":9,"actual_wait":6.0},{"time_slot":"12:05:00","forecast_wait":9,"actual_wait":6.0},{"time_slot":"12:15:00","forecast_wait":9,"actual_wait":6.0},{"time_slot":"12:20:00","forecast_wait":9,"actual_wait":6.0},{"time_slot":"12:25:00","forecast_wait":9,"actual_wait":6.0},{"time_slot":"12:35:00","forecast_wait":9,"actual_wait":6.0},{"time_slot":"12:40:00","forecast_wait":9,"actual_wait":6.0},{"time_slot":"12:45:00","forecast_wait":9,"actual_wait":6.0},{"time_slot":"12:50:00","forecast_wait":9,"actual_wait":6.0},{"time_slot":"12:55:00","forecast_wait":9,"actual_wait":6.0},{"time_slot":"13:50:00","forecast_wait":9,"actual_wait":6.4},{"time_slot":"13:55:00","forecast_wait":9,"actual_wait":6.4},{"time_slot":"14:05:00","forecast_wait":9,"actual_wait":6.4},{"time_slot":"14:10:00","forecast_wait":9,"actual_wait":6.4},{"time_slot":"14:15:00","forecast_wait":9,"actual_wait":6.4},{"time_slot":"14:20:00","forecast_wait":9,"actual_wait":6.4},{"time_slot":"14:30:00","forecast_wait":9,"actual_wait":6.4},{"time_slot":"14:35:00","forecast_wait":9,"actual_wait":6.4},{"time_slot":"14:40:00","forecast_wait":9,"actual_wait":6.4},{"time_slot":"14:45:00","forecast_wait":9,"actual_wait":6.4},{"time_slot":"14:55:00","forecast_wait":9,"actual_wait":6.4},{"time_slot":"22:40:00","forecast_wait":7,"actual_wait":6.0},{"time_slot":"22:45:00","forecast_wait":7,"actual_wait":6.0}]