[{"time_slot":"09:30:00","forecast_wait":5,"actual_wait":2.0},{"time_slot":"19:00:00","forecast_wait":10,"actual_wait":3.5},{"time_slot":"19:05:00","forecast_wait":10,"actual_wait":3.5},{"time_slot":"19:10:00","forecast_wait":10,"actual_wait":3.5},{"time_slot":"19:15:00","forecast_wait":10,"actual_wait":3.5},{"time_slot":"19:20:00","forecast_wait":10,"actual_wait":3.5},{"time_slot":"19:25:00","forecast_wait":10,"actual_wait":3.5},{"time_slot":"19:30:00","forecast_wait":10,"actual_wait":5.3},{"time_slot":"19:35:00","forecast_wait":10,"actual_wait":5.4},{"time_slot":"19:40:00","forecast_wait":10,"actual_wait":5.4},{"time_slot":"19:45:00","forecast_wait":10,"actual_wait":5.5},{"time_slot":"19:50:00","forecast_wait":10,"actual_wait":5.5},{"time_slot":"19:55:00","forecast_wait":10,"actual_wait":5.5},{"time_slot":"20:00:00","forecast_wait":15,"actual_wait":5.5}]