{
  "current_step": "ETL",
  "etl_progress": "31/36 (86%) [2026-02-07]",
  "steps": {
    "etl": "pending",
    "dimensions": "pending",
    "aggregates": "pending",
    "report": "pending"
  },
  "queue_times": {
    "status": "Active",
    "last_fetch": "18:24:29",
    "samples": [
      {
        "name": "MK44",
        "wait": "15"
      },
      {
        "name": "MK39",
        "wait": "25"
      },
      {
        "name": "MK21",
        "wait": "20"
      },
      {
        "name": "MK96",
        "wait": "30"
      },
      {
        "name": "MK210",
        "wait": "30"
      },
      {
        "name": "MK18",
        "wait": "10"
      }
    ]
  },
  "last_updated": "2026-02-07T18:25:01.651590-05:00"
}
