{
  "current_step": "WTI",
  "etl_progress": "36/36 (100%) [2026-02-08]",
  "steps": {
    "etl": "done",
    "dimensions": "done",
    "aggregates": "done",
    "report": "done"
  },
  "queue_times": {
    "status": "Active",
    "last_fetch": "23:06:25",
    "samples": [
      {
        "name": "MK45",
        "wait": "5"
      },
      {
        "name": "MK191",
        "wait": "40"
      },
      {
        "name": "MK44",
        "wait": "5"
      }
    ]
  },
  "last_updated": "2026-02-08T23:10:01.597744-05:00"
}
