{
  "current_step": "ETL",
  "etl_progress": "31/36 (86%) [2026-02-07]",
  "steps": {
    "etl": "pending",
    "dimensions": "pending",
    "aggregates": "pending",
    "report": "pending"
  },
  "queue_times": {
    "status": "Active",
    "last_fetch": "15:13:55",
    "samples": [
      {
        "name": "MK191",
        "wait": "90"
      },
      {
        "name": "MK43",
        "wait": "5"
      },
      {
        "name": "MK21",
        "wait": "20"
      },
      {
        "name": "MK23",
        "wait": "30"
      },
      {
        "name": "MK177",
        "wait": "40"
      },
      {
        "name": "MK13",
        "wait": "45"
      }
    ]
  },
  "last_updated": "2026-02-07T15:15:01.810211-05:00"
}
